pcan/PCANBasic.dll
pcan/PCANBasic.py
pcan/__init__.py
pcan/wrapper.py
pcan_wrapper-0.0.3.dist-info/LICENSE
pcan_wrapper-0.0.3.dist-info/METADATA
pcan_wrapper-0.0.3.dist-info/WHEEL
pcan_wrapper-0.0.3.dist-info/top_level.txt
pcan_wrapper-0.0.3.dist-info/RECORD
