Metadata-Version: 2.1
Name: pcan-wrapper
Version: 0.0.3
Summary: Simple wrapper around PEAK-System Technik GmbH CAN SDK
Home-page: https://github.com/igrekus/pcan_wrapper
Author: igrekus
Author-email: 
License: UNKNOWN
Platform: UNKNOWN
Classifier: Programming Language :: Python :: 3
Classifier: License :: OSI Approved :: MIT License
Classifier: Operating System :: OS Independent
Requires-Python: >=3.6
